<?xml version="1.0" encoding="UTF-8"?>
<beans
  xmlns="http://www.springframework.org/schema/beans"
  xmlns:xsi="http://www.w3.org/2001/XMLSchema-instance"
  xsi:schemaLocation="
    http://www.springframework.org/schema/beans http://www.springframework.org/schema/beans/spring-beans.xsd"
    >

  <bean name="handReader" class="pokerga.HandReader">
    <property name="file" value="data/poker-hand-training-true.data"/>
    <property name="maxHands" value="1000" />
  </bean>

  <bean name="randomOrganism" class="pokerga.init.RandomOrganism">
    <property name="length" value="256" />
    <property name="maxOpCode" value="0x90" />
  </bean>

  <bean name="initialPopulation" class="pokerga.init.InitialPopulation">
    <property name="size" value="100" />
    <property name="organismSupplier" ref="randomOrganism" />
  </bean>

  <bean name="interpreter" class="pokerga.Interpreter">
    <property name="maxDepth" value="4" />
    <property name="maxStack" value="4096" />
  </bean>

  <bean name="mutator" class="pokerga.mut.IdentityMutator">
  </bean>

  <bean class="pokerga.Evaluator">
    <property name="handReader" ref="handReader" />
    <property name="initialPopulation" ref="initialPopulation" />
    <property name="interpreter" ref="interpreter" />
    <property name="mutator" ref="mutator" />
    <property name="maxGenerations" value="1" />
  </bean>

</beans>
